[
  {
    "id": "disney-parks-blog",
    "name": "Disney Parks Blog",
    "sourceType": "rssArticle",
    "feedURL": "https://disneyparks.disney.go.com/blog/feed/",
    "homepageURL": "https://disneyparks.disney.go.com/blog/",
    "trustLabel": "official",
    "categoryTags": ["parksNews", "official"],
    "isEnabled": true,
    "isDefaultEnabled": true,
    "isCustom": false,
    "isRecommended": true,
    "description": "Official Disney Parks news and announcements.",
    "artworkURL": null,
    "lastRefreshAt": null,
    "lastRefreshSucceeded": null,
    "lastErrorMessage": null
  },
  {
    "id": "disney-food-blog",
    "name": "Disney Food Blog",
    "sourceType": "rssArticle",
    "feedURL": "https://www.disneyfoodblog.com/feed/",
    "homepageURL": "https://www.disneyfoodblog.com/",
    "trustLabel": "verifiedNews",
    "categoryTags": ["food", "parksNews", "community"],
    "isEnabled": true,
    "isDefaultEnabled": true,
    "isCustom": false,
    "isRecommended": true,
    "description": "Disney dining news, reviews, and tips.",
    "artworkURL": null,
    "lastRefreshAt": null,
    "lastRefreshSucceeded": null,
    "lastErrorMessage": null
  },
  {
    "id": "wdw-news-today",
    "name": "WDW News Today",
    "sourceType": "rssArticle",
    "feedURL": "https://wdwnt.com/feed/",
    "homepageURL": "https://wdwnt.com/",
    "trustLabel": "verifiedNews",
    "categoryTags": ["parksNews", "community"],
    "isEnabled": true,
    "isDefaultEnabled": true,
    "isCustom": false,
    "isRecommended": true,
    "description": "Breaking Walt Disney World news and updates.",
    "artworkURL": null,
    "lastRefreshAt": null,
    "lastRefreshSucceeded": null,
    "lastErrorMessage": null
  },
  {
    "id": "inside-the-magic",
    "name": "Inside the Magic",
    "sourceType": "rssArticle",
    "feedURL": "https://insidethemagic.net/feed/",
    "homepageURL": "https://insidethemagic.net/",
    "trustLabel": "communitySource",
    "categoryTags": ["parksNews", "community"],
    "isEnabled": true,
    "isDefaultEnabled": true,
    "isCustom": false,
    "isRecommended": false,
    "description": "Rumors and mixed-reliability Disney parks coverage.",
    "artworkURL": null,
    "lastRefreshAt": null,
    "lastRefreshSucceeded": null,
    "lastErrorMessage": null
  },
  {
    "id": "the-dis",
    "name": "The DIS",
    "sourceType": "rssArticle",
    "feedURL": "https://www.wdwinfo.com/feed/",
    "homepageURL": "https://www.wdwinfo.com/",
    "trustLabel": "communitySource",
    "categoryTags": ["parksNews", "planning", "community"],
    "isEnabled": true,
    "isDefaultEnabled": true,
    "isCustom": false,
    "isRecommended": false,
    "description": "DisBoards news and Walt Disney World trip planning.",
    "artworkURL": null,
    "lastRefreshAt": null,
    "lastRefreshSucceeded": null,
    "lastErrorMessage": null
  },
  {
    "id": "chip-and-company",
    "name": "Chip and Company",
    "sourceType": "rssArticle",
    "feedURL": "https://chipandco.com/feed/",
    "homepageURL": "https://chipandco.com/",
    "trustLabel": "verifiedNews",
    "categoryTags": ["parksNews", "food", "community"],
    "isEnabled": true,
    "isDefaultEnabled": true,
    "isCustom": false,
    "isRecommended": true,
    "description": "Popular Disney news, food, and parks coverage.",
    "artworkURL": null,
    "lastRefreshAt": null,
    "lastRefreshSucceeded": null,
    "lastErrorMessage": null
  },
  {
    "id": "disney-tourist-blog",
    "name": "Disney Tourist Blog",
    "sourceType": "rssArticle",
    "feedURL": "https://www.disneytouristblog.com/feed/",
    "homepageURL": "https://www.disneytouristblog.com/",
    "trustLabel": "verifiedNews",
    "categoryTags": ["parksNews", "planning", "community"],
    "isEnabled": false,
    "isDefaultEnabled": false,
    "isCustom": false,
    "isRecommended": false,
    "description": "In-depth Disney trip planning and park guides.",
    "artworkURL": null,
    "lastRefreshAt": null,
    "lastRefreshSucceeded": null,
    "lastErrorMessage": null
  },
  {
    "id": "blog-mickey",
    "name": "Blog Mickey",
    "sourceType": "rssArticle",
    "feedURL": "https://blogmickey.com/feed/",
    "homepageURL": "https://blogmickey.com/",
    "trustLabel": "communitySource",
    "categoryTags": ["parksNews", "community"],
    "isEnabled": false,
    "isDefaultEnabled": false,
    "isCustom": false,
    "isRecommended": false,
    "description": "Walt Disney World news and photo reports.",
    "artworkURL": null,
    "lastRefreshAt": null,
    "lastRefreshSucceeded": null,
    "lastErrorMessage": null
  },
  {
    "id": "touringplans-blog",
    "name": "TouringPlans Blog",
    "sourceType": "rssArticle",
    "feedURL": "https://touringplans.com/blog/feed/",
    "homepageURL": "https://touringplans.com/",
    "trustLabel": "verifiedNews",
    "categoryTags": ["planning", "community"],
    "isEnabled": false,
    "isDefaultEnabled": false,
    "isCustom": false,
    "isRecommended": false,
    "description": "Data-driven Disney park touring strategies and news.",
    "artworkURL": null,
    "lastRefreshAt": null,
    "lastRefreshSucceeded": null,
    "lastErrorMessage": null
  },
  {
    "id": "kenny-the-pirate",
    "name": "Kenny the Pirate",
    "sourceType": "rssArticle",
    "feedURL": "https://www.kennythepirate.com/feed/",
    "homepageURL": "https://www.kennythepirate.com/",
    "trustLabel": "communitySource",
    "categoryTags": ["planning", "community"],
    "isEnabled": false,
    "isDefaultEnabled": false,
    "isCustom": false,
    "isRecommended": false,
    "description": "Disney trip planning tips and character dining guides.",
    "artworkURL": null,
    "lastRefreshAt": null,
    "lastRefreshSucceeded": null,
    "lastErrorMessage": null
  },
  {
    "id": "attractions-magazine",
    "name": "Attractions Magazine",
    "sourceType": "rssArticle",
    "feedURL": "https://attractionsmagazine.com/feed/",
    "homepageURL": "https://attractionsmagazine.com/",
    "trustLabel": "verifiedNews",
    "categoryTags": ["parksNews", "attractions", "community"],
    "isEnabled": false,
    "isDefaultEnabled": false,
    "isCustom": false,
    "isRecommended": false,
    "description": "Theme park and attractions news coverage.",
    "artworkURL": null,
    "lastRefreshAt": null,
    "lastRefreshSucceeded": null,
    "lastErrorMessage": null
  },
  {
    "id": "laughing-place",
    "name": "Laughing Place",
    "sourceType": "rssArticle",
    "feedURL": "https://www.laughingplace.com/w/feed/",
    "homepageURL": "https://www.laughingplace.com/",
    "trustLabel": "verifiedNews",
    "categoryTags": ["parksNews", "community"],
    "isEnabled": false,
    "isDefaultEnabled": false,
    "isCustom": false,
    "isRecommended": false,
    "description": "Disney news and entertainment coverage.",
    "artworkURL": null,
    "lastRefreshAt": null,
    "lastRefreshSucceeded": null,
    "lastErrorMessage": null
  },
  {
    "id": "wdw-radio",
    "name": "WDW Radio",
    "sourceType": "podcastRSS",
    "feedURL": "https://feeds.captivate.fm/wdwradio/",
    "homepageURL": "https://www.wdwradio.com/",
    "trustLabel": "communitySource",
    "categoryTags": ["podcast", "community"],
    "isEnabled": true,
    "isDefaultEnabled": true,
    "isCustom": false,
    "isRecommended": true,
    "description": "Long-running Walt Disney World podcast and community.",
    "artworkURL": null,
    "lastRefreshAt": null,
    "lastRefreshSucceeded": null,
    "lastErrorMessage": null
  },
  {
    "id": "dis-unplugged",
    "name": "The DIS Unplugged",
    "sourceType": "podcastRSS",
    "feedURL": "https://rss.libsyn.com/shows/37406/destinations/100330.xml",
    "homepageURL": "https://www.wdwinfo.com/",
    "trustLabel": "communitySource",
    "categoryTags": ["podcast", "planning", "community"],
    "isEnabled": true,
    "isDefaultEnabled": true,
    "isCustom": false,
    "isRecommended": true,
    "description": "The DIS weekly Disney vacation planning podcast.",
    "artworkURL": null,
    "lastRefreshAt": null,
    "lastRefreshSucceeded": null,
    "lastErrorMessage": null
  },
  {
    "id": "be-our-guest-podcast",
    "name": "Be Our Guest Podcast",
    "sourceType": "podcastRSS",
    "feedURL": "https://beourguestpodcast.com/feed/podcast/",
    "homepageURL": "https://beourguestpodcast.com/",
    "trustLabel": "communitySource",
    "categoryTags": ["podcast", "planning", "community"],
    "isEnabled": true,
    "isDefaultEnabled": true,
    "isCustom": false,
    "isRecommended": true,
    "description": "Popular Disney trip planning and discussion podcast.",
    "artworkURL": null,
    "lastRefreshAt": null,
    "lastRefreshSucceeded": null,
    "lastErrorMessage": null
  },
  {
    "id": "window-to-the-magic",
    "name": "Window to the Magic",
    "sourceType": "podcastRSS",
    "feedURL": "https://feeds.libsyn.com/18340/rss",
    "homepageURL": "https://windowtothemagic.com/",
    "trustLabel": "communitySource",
    "categoryTags": ["podcast", "community"],
    "isEnabled": true,
    "isDefaultEnabled": true,
    "isCustom": false,
    "isRecommended": true,
    "description": "Atmospheric Disney audio tours and park ambience.",
    "artworkURL": null,
    "lastRefreshAt": null,
    "lastRefreshSucceeded": null,
    "lastErrorMessage": null
  },
  {
    "id": "unlocking-the-magic",
    "name": "Unlocking the Magic",
    "sourceType": "podcastRSS",
    "feedURL": "http://feeds.libsyn.com/66005/rss",
    "homepageURL": null,
    "trustLabel": "communitySource",
    "categoryTags": ["podcast", "community"],
    "isEnabled": false,
    "isDefaultEnabled": false,
    "isCustom": false,
    "isRecommended": false,
    "description": "Disney parks stories and interviews podcast.",
    "artworkURL": null,
    "lastRefreshAt": null,
    "lastRefreshSucceeded": null,
    "lastErrorMessage": null
  },
  {
    "id": "disney-dish",
    "name": "Disney Dish with Jim Hill",
    "sourceType": "podcastRSS",
    "feedURL": "https://feeds.megaphone.fm/JHM6229164720",
    "homepageURL": null,
    "trustLabel": "communitySource",
    "categoryTags": ["podcast", "community"],
    "isEnabled": false,
    "isDefaultEnabled": false,
    "isCustom": false,
    "isRecommended": false,
    "description": "Disney history and behind-the-scenes stories with Jim Hill.",
    "artworkURL": null,
    "lastRefreshAt": null,
    "lastRefreshSucceeded": null,
    "lastErrorMessage": null
  },
  {
    "id": "theme-park-shuffle",
    "name": "Theme Park Shuffle",
    "sourceType": "podcastRSS",
    "feedURL": "https://feeds.simplecast.com/NbPREI42",
    "homepageURL": null,
    "trustLabel": "communitySource",
    "categoryTags": ["podcast", "community"],
    "isEnabled": false,
    "isDefaultEnabled": false,
    "isCustom": false,
    "isRecommended": false,
    "description": "Theme park news and discussion podcast.",
    "artworkURL": null,
    "lastRefreshAt": null,
    "lastRefreshSucceeded": null,
    "lastErrorMessage": null
  },
  {
    "id": "main-street-magic-podcast",
    "name": "Main Street Magic Podcast",
    "sourceType": "podcastRSS",
    "feedURL": "https://feeds.simplecast.com/ZY83mmKf",
    "homepageURL": null,
    "trustLabel": "communitySource",
    "categoryTags": ["podcast", "community"],
    "isEnabled": false,
    "isDefaultEnabled": false,
    "isCustom": false,
    "isRecommended": false,
    "description": "Disney storytelling and parks discussion podcast.",
    "artworkURL": null,
    "lastRefreshAt": null,
    "lastRefreshSucceeded": null,
    "lastErrorMessage": null
  },
  {
    "id": "resortloop",
    "name": "ResortLoop Podcast",
    "sourceType": "podcastRSS",
    "feedURL": "https://resortloop.com/feed/podcast/",
    "homepageURL": "https://resortloop.com/",
    "trustLabel": "communitySource",
    "categoryTags": ["podcast", "planning", "community"],
    "isEnabled": false,
    "isDefaultEnabled": false,
    "isCustom": false,
    "isRecommended": false,
    "description": "Walt Disney World news and resort discussion podcast.",
    "artworkURL": null,
    "lastRefreshAt": null,
    "lastRefreshSucceeded": null,
    "lastErrorMessage": null
  },
  {
    "id": "rope-drop-radio",
    "name": "Rope Drop Radio",
    "sourceType": "podcastRSS",
    "feedURL": "https://ropedropradio.libsyn.com/rss",
    "homepageURL": null,
    "trustLabel": "communitySource",
    "categoryTags": ["podcast", "community"],
    "isEnabled": false,
    "isDefaultEnabled": false,
    "isCustom": false,
    "isRecommended": false,
    "description": "Disney parks tips and listener stories podcast.",
    "artworkURL": null,
    "lastRefreshAt": null,
    "lastRefreshSucceeded": null,
    "lastErrorMessage": null
  },
  {
    "id": "reddit-waltdisneyworld",
    "name": "r/WaltDisneyWorld",
    "sourceType": "redditFeed",
    "feedURL": "https://www.reddit.com/r/waltdisneyworld/top.rss?t=week",
    "homepageURL": "https://www.reddit.com/r/waltdisneyworld/",
    "trustLabel": "communitySource",
    "categoryTags": ["social", "parksNews"],
    "isEnabled": true,
    "isDefaultEnabled": true,
    "isCustom": false,
    "isRecommended": true,
    "description": "Top posts this week from the Walt Disney World subreddit.",
    "artworkURL": null,
    "lastRefreshAt": null,
    "lastRefreshSucceeded": null,
    "lastErrorMessage": null
  },
  {
    "id": "reddit-disneylandparis",
    "name": "r/DisneylandParis",
    "sourceType": "redditFeed",
    "feedURL": "https://www.reddit.com/r/disneylandparis/top.rss?t=week",
    "homepageURL": "https://www.reddit.com/r/disneylandparis/",
    "trustLabel": "communitySource",
    "categoryTags": ["social", "parksNews"],
    "isEnabled": false,
    "isDefaultEnabled": false,
    "isCustom": false,
    "isRecommended": false,
    "description": "Top posts this week from the Disneyland Paris subreddit.",
    "artworkURL": null,
    "lastRefreshAt": null,
    "lastRefreshSucceeded": null,
    "lastErrorMessage": null
  },
  {
    "id": "reddit-disneyland",
    "name": "r/Disneyland",
    "sourceType": "redditFeed",
    "feedURL": "https://www.reddit.com/r/disneyland/top.rss?t=week",
    "homepageURL": "https://www.reddit.com/r/disneyland/",
    "trustLabel": "communitySource",
    "categoryTags": ["social", "parksNews"],
    "isEnabled": false,
    "isDefaultEnabled": false,
    "isCustom": false,
    "isRecommended": false,
    "description": "Top posts this week from the Disneyland subreddit.",
    "artworkURL": null,
    "lastRefreshAt": null,
    "lastRefreshSucceeded": null,
    "lastErrorMessage": null
  },
  {
    "id": "reddit-disneyparks",
    "name": "r/DisneyParks",
    "sourceType": "redditFeed",
    "feedURL": "https://www.reddit.com/r/disneyparks/top.rss?t=week",
    "homepageURL": "https://www.reddit.com/r/disneyparks/",
    "trustLabel": "communitySource",
    "categoryTags": ["social", "parksNews"],
    "isEnabled": false,
    "isDefaultEnabled": false,
    "isCustom": false,
    "isRecommended": false,
    "description": "Top posts this week from the Disney Parks subreddit.",
    "artworkURL": null,
    "lastRefreshAt": null,
    "lastRefreshSucceeded": null,
    "lastErrorMessage": null
  },
  {
    "id": "reddit-disney",
    "name": "r/disney",
    "sourceType": "redditFeed",
    "feedURL": "https://www.reddit.com/r/disney/top.rss?t=week",
    "homepageURL": "https://www.reddit.com/r/disney/",
    "trustLabel": "communitySource",
    "categoryTags": ["social"],
    "isEnabled": false,
    "isDefaultEnabled": false,
    "isCustom": false,
    "isRecommended": false,
    "description": "Top posts this week from the Disney subreddit.",
    "artworkURL": null,
    "lastRefreshAt": null,
    "lastRefreshSucceeded": null,
    "lastErrorMessage": null
  },
  {
    "id": "dfbguide-youtube",
    "name": "Disney Food Blog",
    "sourceType": "youtubeChannel",
    "feedURL": "https://www.youtube.com/feeds/videos.xml?channel_id=UCnpWedLQdHpZqhgTLdB9Yyg",
    "homepageURL": "https://www.youtube.com/c/DFBGuide",
    "trustLabel": "verifiedNews",
    "categoryTags": ["video", "food", "community"],
    "isEnabled": true,
    "isDefaultEnabled": true,
    "isCustom": false,
    "isRecommended": true,
    "description": "Disney food reviews and dining videos by DFBGuide.",
    "artworkURL": null,
    "lastRefreshAt": null,
    "lastRefreshSucceeded": null,
    "lastErrorMessage": null
  },
  {
    "id": "allears-youtube",
    "name": "AllEars.net",
    "sourceType": "youtubeChannel",
    "feedURL": "https://www.youtube.com/feeds/videos.xml?channel_id=UCfzP_CiebRdveD9rRZv5Ndw",
    "homepageURL": "https://www.youtube.com/c/AllEarsNet",
    "trustLabel": "verifiedNews",
    "categoryTags": ["video", "community"],
    "isEnabled": true,
    "isDefaultEnabled": true,
    "isCustom": false,
    "isRecommended": true,
    "description": "Disney parks videos, tips, and resort guides.",
    "artworkURL": null,
    "lastRefreshAt": null,
    "lastRefreshSucceeded": null,
    "lastErrorMessage": null
  },
  {
    "id": "tim-tracker-youtube",
    "name": "The Tim Tracker",
    "sourceType": "youtubeChannel",
    "feedURL": "https://www.youtube.com/feeds/videos.xml?channel_id=UCd18OhMfRmjMjzSHP7Zrzmw",
    "homepageURL": "https://www.youtube.com/c/TheTimTracker",
    "trustLabel": "communitySource",
    "categoryTags": ["video", "community"],
    "isEnabled": true,
    "isDefaultEnabled": true,
    "isCustom": false,
    "isRecommended": true,
    "description": "Disney World vlog and day-in-the-park videos.",
    "artworkURL": null,
    "lastRefreshAt": null,
    "lastRefreshSucceeded": null,
    "lastErrorMessage": null
  },
  {
    "id": "wdwnt-youtube",
    "name": "WDW News Today",
    "sourceType": "youtubeChannel",
    "feedURL": "https://www.youtube.com/feeds/videos.xml?channel_id=UCRIVd5Ci1bTQqJB_T4q_Jgg",
    "homepageURL": "https://www.youtube.com/c/WDWNewsToday",
    "trustLabel": "verifiedNews",
    "categoryTags": ["video", "community"],
    "isEnabled": true,
    "isDefaultEnabled": true,
    "isCustom": false,
    "isRecommended": false,
    "description": "WDW News Today YouTube channel for Disney parks video coverage.",
    "artworkURL": null,
    "lastRefreshAt": null,
    "lastRefreshSucceeded": null,
    "lastErrorMessage": null
  },
  {
    "id": "mammoth-club-youtube",
    "name": "Mammoth Club",
    "sourceType": "youtubeChannel",
    "feedURL": "https://www.youtube.com/feeds/videos.xml?channel_id=UCpSgg_ECBj25s9moCDfSTsA",
    "homepageURL": "https://www.youtube.com/channel/UCpSgg_ECBj25s9moCDfSTsA",
    "trustLabel": "communitySource",
    "categoryTags": ["video", "community"],
    "isEnabled": false,
    "isDefaultEnabled": false,
    "isCustom": false,
    "isRecommended": false,
    "description": "Disney and theme park video coverage.",
    "artworkURL": null,
    "lastRefreshAt": null,
    "lastRefreshSucceeded": null,
    "lastErrorMessage": null
  },
  {
    "id": "paging-mr-morrow-youtube",
    "name": "Paging Mr. Morrow",
    "sourceType": "youtubeChannel",
    "feedURL": "https://www.youtube.com/feeds/videos.xml?channel_id=UCscn2aSpMrS2U_mf7OF-UwQ",
    "homepageURL": "https://www.youtube.com/channel/UCV2YqW7kG6P4R3Kz6H7b6bg",
    "trustLabel": "communitySource",
    "categoryTags": ["video", "community"],
    "isEnabled": false,
    "isDefaultEnabled": false,
    "isCustom": false,
    "isRecommended": false,
    "description": "Disney parks exploration and hidden detail videos.",
    "artworkURL": null,
    "lastRefreshAt": null,
    "lastRefreshSucceeded": null,
    "lastErrorMessage": null
  },
  {
    "id": "super-enthused-youtube",
    "name": "Super Enthused",
    "sourceType": "youtubeChannel",
    "feedURL": "https://www.youtube.com/feeds/videos.xml?channel_id=UCLuKPtTOtrPVaBuZBuDYbaw",
    "homepageURL": "https://www.youtube.com/channel/UCnQH4a4Z9gY1dQ8k6Z1b0bA",
    "trustLabel": "communitySource",
    "categoryTags": ["video", "community"],
    "isEnabled": false,
    "isDefaultEnabled": false,
    "isCustom": false,
    "isRecommended": false,
    "description": "Disney and theme park enthusiast video coverage.",
    "artworkURL": null,
    "lastRefreshAt": null,
    "lastRefreshSucceeded": null,
    "lastErrorMessage": null
  },
  {
    "id": "ordinary-adventures-youtube",
    "name": "Ordinary Adventures",
    "sourceType": "youtubeChannel",
    "feedURL": "https://www.youtube.com/feeds/videos.xml?channel_id=UCZrh7jGCGMnxu5GZ_EuJaMw",
    "homepageURL": "https://www.youtube.com/channel/UCn4d3i0pGJtXk6b9Jf7Y2xQ",
    "trustLabel": "communitySource",
    "categoryTags": ["video", "community"],
    "isEnabled": false,
    "isDefaultEnabled": false,
    "isCustom": false,
    "isRecommended": false,
    "description": "Everyday Disney vacation vlogs and park day videos.",
    "artworkURL": null,
    "lastRefreshAt": null,
    "lastRefreshSucceeded": null,
    "lastErrorMessage": null
  }
]
